nada_numpy/__init__.py
nada_numpy/array.py
nada_numpy/client.py
nada_numpy/context.py
nada_numpy/funcs.py
nada_numpy/legacy_client.py
nada_numpy/nada_typing.py
nada_numpy/types.py
nada_numpy/utils.py
nada_numpy-0.6.0.dist-info/LICENSE
nada_numpy-0.6.0.dist-info/METADATA
nada_numpy-0.6.0.dist-info/WHEEL
nada_numpy-0.6.0.dist-info/RECORD
