Metadata-Version: 2.1
Name: nada-numpy
Version: 0.6.0
Summary: Nada-Numpy is a Python library designed for algebraic operations on NumPy-like array objects on top of Nada DSL and Nillion Network.
Author: José Cabrero-Holgueras
Author-email: jose.cabrero@nillion.com
Requires-Python: >=3.10,<4.0
Classifier: Programming Language :: Python :: 3
Classifier: Programming Language :: Python :: 3.10
Classifier: Programming Language :: Python :: 3.11
Classifier: Programming Language :: Python :: 3.12
Classifier: Programming Language :: Python :: 3.13
Provides-Extra: examples
Provides-Extra: linter
Requires-Dist: black (==24.8.0) ; extra == "linter"
Requires-Dist: isort (>=5.13.2,<6.0.0) ; extra == "linter"
Requires-Dist: nada-dsl (>=0.7.1,<0.8.0)
Requires-Dist: nada-test (>=0.6.0,<0.7.0)
Requires-Dist: nillion-client (>=0.1.0,<0.2.0)
Requires-Dist: nillion-python-helpers (>=0.3.0,<0.4.0)
Requires-Dist: numpy (>=1.26.4,<2.0.0)
Requires-Dist: py-nillion-client (>=0.6.0,<0.7.0)
Requires-Dist: scikit-learn (>=1.5.1,<2.0.0) ; extra == "examples"
